otzyvy_co/__init__.py
otzyvy_co/otzyvy_co.py
otzyvy_co-0.1.0.dist-info/LICENSE
otzyvy_co-0.1.0.dist-info/METADATA
otzyvy_co-0.1.0.dist-info/WHEEL
otzyvy_co-0.1.0.dist-info/top_level.txt
otzyvy_co-0.1.0.dist-info/RECORD
