Metadata-Version: 2.1
Name: otzyvy-co
Version: 0.1.0
Summary: otzyvy_co
Home-page: https://github.com/NMelis/otzyvy_co
Author: NMelis
Author-email: melis.zhoroev+scrubbers@gmail.com
License: MIT license
Keywords: otzyvy_co
Platform: UNKNOWN
Classifier: Development Status :: 2 - Pre-Alpha
Classifier: Intended Audience :: Developers
Classifier: License :: OSI Approved :: MIT License
Classifier: Natural Language :: English
Classifier: Programming Language :: Python :: 2
Classifier: Programming Language :: Python :: 2.7
Classifier: Programming Language :: Python :: 3
Classifier: Programming Language :: Python :: 3.4
Classifier: Programming Language :: Python :: 3.5
Classifier: Programming Language :: Python :: 3.6
Classifier: Programming Language :: Python :: 3.7
Requires-Dist: requests
Requires-Dist: bs4
